i2p/__init__.py
i2p/crypto.py
i2p/datatypes.py
i2p/util.py
i2p/socket/__init__.py
i2p/socket/__main__.py
i2p/socket/exceptions.py
i2p/socket/sam/__init__.py
i2p/socket/sam/simple.py
i2p.socket-0.3.1.dist-info/DESCRIPTION.rst
i2p.socket-0.3.1.dist-info/METADATA
i2p.socket-0.3.1.dist-info/RECORD
i2p.socket-0.3.1.dist-info/WHEEL
i2p.socket-0.3.1.dist-info/metadata.json
i2p.socket-0.3.1.dist-info/top_level.txt
