Metadata-Version: 2.0
Name: i2p.socket
Version: 0.3.1
Summary: I2P socket module
Home-page: https://github.com/majestrate/i2p.socket
Author: Jeff
Author-email: ampernand@gmail.com
License: MIT
Download-URL: https://github.com/majestrate/i2p.socket/tarball/0.3.1
Keywords: i2p,socket
Platform: UNKNOWN
Classifier: Development Status :: 3 - Alpha
Classifier: Intended Audience :: Developers
Classifier: License :: Public Domain
Classifier: Operating System :: OS Independent
Classifier: Programming Language :: Python
Classifier: Programming Language :: Python :: 2.6
Classifier: Programming Language :: Python :: 2.7
Classifier: Programming Language :: Python :: 3
Classifier: Programming Language :: Python :: 3.3
Classifier: Programming Language :: Python :: 3.4
Classifier: Topic :: Internet
Requires-Dist: enum34 (>=1.0)
Requires-Dist: future (>=0.14.0)
Requires-Dist: libnacl (>=1.4.3)
Requires-Dist: pycrypto
Requires-Dist: pyelliptic (==1.5.6)
